{
  "adv (1)": {
    "text1": "",
    "text2": "",
    "extension": "jpg"
  },
  "adv (2)": {
    "text1": "",
    "text2": "",
    "extension": "jpg"
  },
  "adv (3)": {
    "text1": "",
    "text2": "",
    "extension": "jpg"
  },
  "adv (4)": {
    "text1": "",
    "text2": "",
    "extension": "jpg"
  },
  "adv (5)": {
    "text1": "",
    "text2": "",
    "extension": "jpg"
  },
  "adv (6)": {
    "text1": "",
    "text2": "",
    "extension": "jpg"
  },
  "adv (7)": {
    "text1": "",
    "text2": "",
    "extension": "jpg"
  },
  "adv (8)": {
    "text1": "",
    "text2": "",
    "extension": "jpg"
  },
  "adv (9)": {
    "text1": "",
    "text2": "",
    "extension": "jpg"
  },
  "adv (10)": {
    "text1": "",
    "text2": "",
    "extension": "jpg"
  },
  "adv (11)": {
    "text1": "",
    "text2": "",
    "extension": "jpg"
  },
  "adv (12)": {
    "text1": "",
    "text2": "",
    "extension": "jpg"
  },
  "adv (13)": {
    "text1": "",
    "text2": "",
    "extension": "jpg"
  },
  "adv (14)": {
    "text1": "",
    "text2": "",
    "extension": "jpg"
  },
  "adv (15)": {
    "text1": "",
    "text2": "",
    "extension": "jpg"
  },
  "adv (16)": {
    "text1": "",
    "text2": "",
    "extension": "jpg"
  },
  "adv (17)": {
    "text1": "",
    "text2": "",
    "extension": "jpg"
  },
  "adv (18)": {
    "text1": "",
    "text2": "",
    "extension": "jpg"
  },
  "adv (19)": {
    "text1": "",
    "text2": "",
    "extension": "jpg"
  },
  "adv (20)": {
    "text1": "",
    "text2": "",
    "extension": "jpg"
  },
  "adv (21)": {
    "text1": "",
    "text2": "",
    "extension": "jpg"
  },
  "adv (22)": {
    "text1": "",
    "text2": "",
    "extension": "jpg"
  },
  "adv (23)": {
    "text1": "",
    "text2": "",
    "extension": "jpg"
  },
  "adv (24)": {
    "text1": "",
    "text2": "",
    "extension": "jpg"
  },
  "adv (25)": {
    "text1": "",
    "text2": "",
    "extension": "jpg"
  },
  "adv (26)": {
    "text1": "",
    "text2": "",
    "extension": "jpg"
  },
  "adv (27)": {
    "text1": "",
    "text2": "",
    "extension": "jpg"
  },
  "adv (28)": {
    "text1": "",
    "text2": "",
    "extension": "jpg"
  },
  "adv (29)": {
    "text1": "",
    "text2": "",
    "extension": "jpg"
  },
  "adv (30)": {
    "text1": "",
    "text2": "",
    "extension": "jpg"
  },
  "adv (31)": {
    "text1": "",
    "text2": "",
    "extension": "jpg"
  },
  "adv (32)": {
    "text1": "",
    "text2": "",
    "extension": "jpg"
  },
  "adv (33)": {
    "text1": "",
    "text2": "",
    "extension": "jpg"
  },
  "adv (34)": {
    "text1": "",
    "text2": "",
    "extension": "jpg"
  },
  "adv (35)": {
    "text1": "",
    "text2": "",
    "extension": "jpg"
  },
  "adv (36)": {
    "text1": "",
    "text2": "",
    "extension": "jpg"
  },
  "adv (37)": {
    "text1": "",
    "text2": "",
    "extension": "jpg"
  },
  "adv (38)": {
    "text1": "",
    "text2": "",
    "extension": "jpg"
  },
  "adv (39)": {
    "text1": "",
    "text2": "",
    "extension": "jpg"
  },
  "adv (40)": {
    "text1": "",
    "text2": "",
    "extension": "jpg"
  },
  "adv (41)": {
    "text1": "",
    "text2": "",
    "extension": "jpg"
  },
  "adv (42)": {
    "text1": "",
    "text2": "",
    "extension": "jpg"
  },
  "adv (43)": {
    "text1": "",
    "text2": "",
    "extension": "jpg"
  },
  "adv (44)": {
    "text1": "",
    "text2": "",
    "extension": "jpg"
  },
  "adv (45)": {
    "text1": "",
    "text2": "",
    "extension": "jpg"
  },
  "adv (46)": {
    "text1": "",
    "text2": "",
    "extension": "jpg"
  },
  "adv (47)": {
    "text1": "",
    "text2": "",
    "extension": "jpg"
  },
  "adv (48)": {
    "text1": "",
    "text2": "",
    "extension": "jpg"
  },
  "adv (49)": {
    "text1": "",
    "text2": "",
    "extension": "jpg"
  },
  "adv (50)": {
    "text1": "",
    "text2": "",
    "extension": "jpg"
  },
  "adv (51)": {
    "text1": "",
    "text2": "",
    "extension": "jpg"
  },
  "adv (52)": {
    "text1": "",
    "text2": "",
    "extension": "jpg"
  },
  "adv (53)": {
    "text1": "",
    "text2": "",
    "extension": "jpg"
  },
  "adv (54)": {
    "text1": "",
    "text2": "",
    "extension": "jpg"
  },
  "adv (55)": {
    "text1": "",
    "text2": "",
    "extension": "jpg"
  },
  "adv (56)": {
    "text1": "",
    "text2": "",
    "extension": "jpg"
  },
  "adv (57)": {
    "text1": "",
    "text2": "",
    "extension": "jpg"
  },
  "adv (58)": {
    "text1": "",
    "text2": "",
    "extension": "jpg"
  },
  "adv (59)": {
    "text1": "",
    "text2": "",
    "extension": "jpg"
  },
  "adv (60)": {
    "text1": "",
    "text2": "",
    "extension": "jpg"
  },
  "adv (61)": {
    "text1": "",
    "text2": "",
    "extension": "jpg"
  },
  "adv (62)": {
    "text1": "",
    "text2": "",
    "extension": "jpg"
  },
  "adv (63)": {
    "text1": "",
    "text2": "",
    "extension": "jpg"
  },
  "adv (64)": {
    "text1": "",
    "text2": "",
    "extension": "jpg"
  },
  "adv (65)": {
    "text1": "",
    "text2": "",
    "extension": "jpg"
  },
  "adv (66)": {
    "text1": "",
    "text2": "",
    "extension": "jpg"
  },
  "adv (67)": {
    "text1": "",
    "text2": "",
    "extension": "jpg"
  },
  "adv (68)": {
    "text1": "",
    "text2": "",
    "extension": "jpg"
  },
  "adv (69)": {
    "text1": "",
    "text2": "",
    "extension": "jpg"
  },
  "adv (70)": {
    "text1": "",
    "text2": "",
    "extension": "jpg"
  },
  "adv (71)": {
    "text1": "",
    "text2": "",
    "extension": "jpg"
  },
  "adv (72)": {
    "text1": "",
    "text2": "",
    "extension": "jpg"
  },
  "adv (73)": {
    "text1": "",
    "text2": "",
    "extension": "jpg"
  },
  "adv (74)": {
    "text1": "",
    "text2": "",
    "extension": "jpg"
  },
  "adv (75)": {
    "text1": "",
    "text2": "",
    "extension": "jpg"
  },
  "adv (76)": {
    "text1": "",
    "text2": "",
    "extension": "jpg"
  },
  "adv (77)": {
    "text1": "",
    "text2": "",
    "extension": "jpg"
  },
  "adv (78)": {
    "text1": "",
    "text2": "",
    "extension": "jpg"
  },
  "adv (79)": {
    "text1": "",
    "text2": "",
    "extension": "jpg"
  },
  "adv (80)": {
    "text1": "",
    "text2": "",
    "extension": "jpg"
  },
  "adv (81)": {
    "text1": "",
    "text2": "",
    "extension": "jpg"
  },
  "adv (82)": {
    "text1": "",
    "text2": "",
    "extension": "jpg"
  },
  "adv (83)": {
    "text1": "",
    "text2": "",
    "extension": "jpg"
  },
  "adv (84)": {
    "text1": "",
    "text2": "",
    "extension": "jpg"
  },
  "adv (85)": {
    "text1": "",
    "text2": "",
    "extension": "jpg"
  },
  "adv (86)": {
    "text1": "",
    "text2": "",
    "extension": "jpg"
  },
  "adv (87)": {
    "text1": "",
    "text2": "",
    "extension": "jpg"
  },
  "adv (88)": {
    "text1": "",
    "text2": "",
    "extension": "jpg"
  },
  "adv (89)": {
    "text1": "",
    "text2": "",
    "extension": "jpg"
  },
  "adv (90)": {
    "text1": "",
    "text2": "",
    "extension": "jpg"
  },
  "adv (91)": {
    "text1": "",
    "text2": "",
    "extension": "jpg"
  },
  "adv (92)": {
    "text1": "",
    "text2": "",
    "extension": "jpg"
  },
  "adv (93)": {
    "text1": "",
    "text2": "",
    "extension": "jpg"
  },
  "adv (94)": {
    "text1": "",
    "text2": "",
    "extension": "jpg"
  },
  "adv (95)": {
    "text1": "",
    "text2": "",
    "extension": "jpg"
  },
  "adv (96)": {
    "text1": "",
    "text2": "",
    "extension": "jpg"
  },
  "adv (97)": {
    "text1": "",
    "text2": "",
    "extension": "jpg"
  },
  "adv (98)": {
    "text1": "",
    "text2": "",
    "extension": "jpg"
  },
  "adv (99)": {
    "text1": "",
    "text2": "",
    "extension": "jpg"
  },
  "adv (100)": {
    "text1": "",
    "text2": "",
    "extension": "jpg"
  },
  "adv (101)": {
    "text1": "",
    "text2": "",
    "extension": "jpg"
  },
  "adv (102)": {
    "text1": "",
    "text2": "",
    "extension": "jpg"
  },
  "adv (103)": {
    "text1": "",
    "text2": "",
    "extension": "jpg"
  },
  "adv (104)": {
    "text1": "",
    "text2": "",
    "extension": "jpg"
  },
  "adv (105)": {
    "text1": "",
    "text2": "",
    "extension": "jpg"
  },
  "adv (106)": {
    "text1": "",
    "text2": "",
    "extension": "jpg"
  },
  "adv (107)": {
    "text1": "",
    "text2": "",
    "extension": "jpg"
  },
  "adv (108)": {
    "text1": "",
    "text2": "",
    "extension": "jpg"
  },
  "adv (109)": {
    "text1": "",
    "text2": "",
    "extension": "jpg"
  },
  "adv (110)": {
    "text1": "",
    "text2": "",
    "extension": "jpg"
  },
  "adv (111)": {
    "text1": "",
    "text2": "",
    "extension": "jpg"
  },
  "adv (112)": {
    "text1": "",
    "text2": "",
    "extension": "jpg"
  },
  "adv (113)": {
    "text1": "",
    "text2": "",
    "extension": "jpg"
  },
  "adv (114)": {
    "text1": "",
    "text2": "",
    "extension": "jpg"
  },
  "adv (115)": {
    "text1": "",
    "text2": "",
    "extension": "jpg"
  },
  "adv (116)": {
    "text1": "",
    "text2": "",
    "extension": "jpg"
  },
  "adv (117)": {
    "text1": "",
    "text2": "",
    "extension": "jpg"
  },
  "adv (118)": {
    "text1": "",
    "text2": "",
    "extension": "jpg"
  },
  "adv (119)": {
    "text1": "",
    "text2": "",
    "extension": "jpg"
  },
  "adv (120)": {
    "text1": "",
    "text2": "",
    "extension": "jpg"
  },
  "adv (121)": {
    "text1": "",
    "text2": "",
    "extension": "jpg"
  },
  "adv (122)": {
    "text1": "",
    "text2": "",
    "extension": "jpg"
  },
  "adv (123)": {
    "text1": "",
    "text2": "",
    "extension": "jpg"
  },
  "adv (124)": {
    "text1": "",
    "text2": "",
    "extension": "jpg"
  },
  "adv (125)": {
    "text1": "",
    "text2": "",
    "extension": "jpg"
  },
  "adv (126)": {
    "text1": "",
    "text2": "",
    "extension": "jpg"
  },
  "adv (127)": {
    "text1": "",
    "text2": "",
    "extension": "jpg"
  },
  "adv (128)": {
    "text1": "",
    "text2": "",
    "extension": "jpg"
  },
  "adv (129)": {
    "text1": "",
    "text2": "",
    "extension": "jpg"
  },
  "adv (130)": {
    "text1": "",
    "text2": "",
    "extension": "jpg"
  }
}